django_svelte/__init__.py
django_svelte/apps.py
django_svelte/conf.py
django_svelte/models.py
django_svelte/views.py
django_svelte/templates/django_svelte/display_svelte.html
django_svelte/templates/django_svelte/display_svelte_css.html
django_svelte/templatetags/__init__.py
django_svelte/templatetags/django_svelte.py
django_svelte-0.2.1.dist-info/LICENSE
django_svelte-0.2.1.dist-info/METADATA
django_svelte-0.2.1.dist-info/WHEEL
django_svelte-0.2.1.dist-info/top_level.txt
django_svelte-0.2.1.dist-info/RECORD
